DESCRIPTION
MANIFEST.in
README
README.rst
setup.py
directoryhash/__init__.py
directoryhash/directoryhash.py
directoryhash.egg-info/PKG-INFO
directoryhash.egg-info/SOURCES.txt
directoryhash.egg-info/dependency_links.txt
directoryhash.egg-info/top_level.txt