Metadata-Version: 1.1
Name: directoryhash
Version: 0.1
Summary: DirectoryHash is a library for Python. It gives an opportunity to get a hash of the destination folder. You can choose file types, which will participate in the calculations.
Home-page: http://yudkin.com.ua
Author: Alexander Yudkin
Author-email: alexander@yudkin.com.ua
License: The MIT License (MIT)
Keywords: directoryhash,directory_hash,hash of directory,directory md5,directory sha1,folder hash,md5 folder,sha1 folder
Platform: UNKNOWN
Classifier: Intended Audience :: Developers
Classifier: Environment :: Web Environment
Classifier: Operating System :: OS Independent
Classifier: Programming Language :: Python
